mini.v
`timescale 1ns / 1ps
////////////////////////////////////////////////////////////////////////////////
// Company: 
// Engineer: 
// 
// Create Date:    15:04:39 10/12/2017 
// Design Name: 
// Module Name:    mini 
// Project Name: 
// Target Devices: 
// Tool versions: 
// Description: 
//
// Dependencies: 
//
// Revision: 
// Revision 0.01 - File Created
// Additional Comments: 
//
/////////////////////////////////////////////////////////////////////////////////
//								Cheatsheet
//OpCode						Process
//0000							ADD R1,R2,R3	(adds R2 to R1 and stores it in R3)
//0001							SUB R1,R2,R3	(subracts R2 from R1 and stores it in R3)
//0010							AND R1,R2,R3	(bitwise and on R1,R2 and stores in R3)
//0011							OR R1,R2,R3		(bitwise or on R1,R2 and stores in R3)
//0100							LS R1,R2,R3		(left shifts R1 by R2 unit and stores in R3)
//0101							RS R1,R2,R3		(right shifts R1 by R2 unit and stores in R3)
//0110							INC R1			(increments by 1 value)
//0111							DEC R1			(decrements by 1 value)
//1000							MOV R5,R3 		(moves data from R5 to R3)
//1001							LD R5,0xf 		(loads R5 with data)
//1010							ST R5,M1 		(stores R5 onto external memory address)
//1011							LDI R5,M3  		(loads onto R5 from memory address)
//1100							STI M3,0xf		(stores the data immediately)
//1101							BNE C1 C2		(branches to C1 if zero flag is present else to C2)
//1110							BREC C1 C2		(branches to C1 if carry flag is present else to C2)
//1111							STOP			(stops the program)
// Flags[overflow/underflow,zero]
/////////////////////////////////////////////////////////////////////////////////


module mini(clk,L,W,R,S);
wire[3:0] adrs;
wire[7:0] dtin,dm0,dm1,dm2;
wire[2:0] cbus;
wire[1:0] flag;
output wire W,R,L,S;
input wire clk;
wire[7:0] out;
reg[7:0] ram[0:15];
reg[7:0] bus;
assign dm0=ram[5];
assign dm1=ram[3];							//Just to check whether store is working
assign dm2=ram[4];
cu ControlUnit(clk,adrs,dtin,W,R,cbus,L,S,flag);
eu ExecutionUnit(adrs,dtin,W,R,cbus,L,out,S,bus,flag);

always@(*) begin
if (L&S) begin
	bus<=ram[adrs];
	end
if(W&S) begin
	ram[adrs]=out;
	end
end
endmodule



module cu(clk,adrs,dtin,W,R,cbus,L,S,flag);
input wire clk;
output wire[3:0] adrs;
output wire[7:0] dtin;
output wire[2:0] cbus;
input wire[1:0] flag;
output wire W,R,L,S;
wire[4:0] pc;
wire [4:0] countadd;
wire [15:0] instruc;
wire count;

counter ProgramCounter(clk,count,pc,countadd);
instrucrdec InstructionDecoder(instruc,clk,adrs,dtin,W,R,cbus,L,S,count,flag,countadd);
progmemory ProgramMemory(clk,pc,instruc);

endmodule

module counter(clk,count,pc,countadd);
input wire clk,count;
output reg[4:0] pc;
input wire [4:0] countadd;
initial begin 
pc=0;
end
always@(posedge(count))begin
	if(countadd==5'b11111) begin
		pc=pc+1;
		end
	else begin
		pc=countadd;
		end
	end
endmodule

module progmemory(clk,pc,instruc);
reg[15:0] pmem[0:31];
output reg[15:0] instruc;
input wire [4:0] pc;
input wire clk;
initial begin
	pmem[0]= 16'b1001_0110_00001000;   //LD R6,8b'00000100;  Factorial of 8
    pmem[1]= 16'b1001_0111_00000010;   //LD R7,8b'00000010;
    pmem[2]= 16'b1001_1000_00000000;   //LD R8,8b'00000000;
    pmem[3]= 16'b1000_0110_0100_xxxx;  //MOV R6, R4;
    pmem[4]= 16'b0001_0100_0111_0100;  //SUB R4, R7,R4;
    pmem[5]= 16'b1000_0110_0011_xxxx;  //MOV R6,R3
    pmem[6]= 16'b1000_1000_1001_xxxx;  //MOV R8,R9
    pmem[7]= 16'b1000_0100_0101_xxxx;  //MOV R4, R5; 
	pmem[8]= 16'b0000_1000_1001_1000; //ADD R8, R9, R8;       
    pmem[9]= 16'b0000_0110_0011_0110;  //ADD R6, R3, R6;
    pmem[10]= 16'b1110_01011_01100_xx;  //BREC 11,12 ;
    pmem[11]= 16'b0110_1000_xxxxxxxx; //INC R8;
    pmem[12]= 16'b0111_0101_xxxxxxxx; //DEC R5;
    pmem[13]= 16'b1101_01110_01000_xx; //BNE 14,8;                   
    pmem[14]= 16'b0111_0100_xxxxxxxx; //DEC R4;
    pmem[15]= 16'b1101_10000_00101_xx; //BNE 16,5;
    pmem[16]= 16'b1010_0110_0100_xxxx; //ST R6,M3;  
    pmem[17]= 16'b1010_1000_0011_xxxx; //ST R8,M4;  
	pmem[18]= 16'b1100_0101_00000000;  //STI M5,0x00000000                           
    pmem[19]= 16'b1111_xxxxxxxxxxxx;   //STOP 
	
	// pmem[0]= 16'b1001_0110_00000100;  //LD R6,8b'00000100;  Factorial of 5
	// pmem[1]= 16'b1001_0111_00000010;  //LD R7,8b'00000010;
    // pmem[2]= 16'b1000_0110_0100_xxxx;  //MOV R6, R4;
    // pmem[3]= 16'b0001_0100_0111_0100;  //SUB R4, R7,R4;
    // pmem[4]= 16'b1000_0110_0011_xxxx;  //MOV R6,R3
    // pmem[5]= 16'b1000_0100_0101_0001;  //MOV R4, R5;        
    // pmem[6]= 16'b0000_0110_0011_0110;//ADD R6, R3, R6; 
    // pmem[7]= 16'b0111_0101_xxxxxxxx;//DEC R5;
    // pmem[8]= 16'b1101_01001_00110_xx;//BNE 9,6;                   
    // pmem[9]= 16'b0111_0100_xxxxxxxx;//DEC R4
    // pmem[10]= 16'b1101_01011_00100_xx;//BNE 11,4;
    // pmem[11]= 16'b1010_0110_0011_xxxx;//ST R6,M3;     
    // pmem[12]= 16'b1111_xxxxxxxxxxxx;//STOP   
end
always@(*)begin
 instruc=pmem[pc];
end 
endmodule

module instrucrdec(instruc,clk,adrs,dtin,W,R,cbus,L,S,count,flag,countadd);
input wire clk;
input wire[1:0] flag;
output reg[3:0] adrs;
output reg count;
output reg[2:0] cbus;
output reg W,R,L,S;
output reg[4:0] countadd;
reg wr,re,ld;
reg[3:0] addr;
output reg [7:0] dtin;
reg [7:0] d_in;
input wire[15:0] instruc;
reg[3:0] start,a,b,c,d,e,f,g,st;
initial begin		//Assigning all possible states in 3 bit
count=0;
start=3'b000;
a=3'b001;
b=3'b010;
c=3'b011;
d=3'b100;
e=3'b101;
f=3'b110;
g=3'b111;
st=start;
countadd=5'b11111;
end
always@(posedge clk)begin
	
	if(st==f)
	st=g;
	if(st==e)
	st=f;
	if(st==d)
	st=e;
	if(st==c)
	st=d;
	if(st==b)
	st=c;
	if(st==a)
	st=b;
	if(st==start)	begin
	st=a;
	count=0;
	countadd=5'b11111;
	end

	if(instruc[15]==1'b0) begin			//ALU Operations
	if(st==a) begin
	W=0;
	R=1;
	adrs = instruc[11:8];
	end
	if(st==b) begin
	W=1;
	R=0;
	adrs = 4'b0000;
	end
	if(st==c) begin
	W=0;
	R=1;
	adrs = instruc[7:4];
	end
	if(st==d) begin
	W=1;
	R=0;
	adrs = 4'b001;
	end
	if(st==e) begin
	W=0;
	cbus = instruc[14:12];
	end
	if(st==f) begin
	R=1;
	adrs= 4'b0010;
	end	
	if(st==g) begin
	R=0;
	W=1;
	if(instruc[14]==1'b0|instruc[14:13]==2'b10)begin
	adrs= instruc[3:0];
	end
	else if(instruc[14:13]==2'b11)begin
	adrs= instruc[11:8];
	end
	count=1;
	st=start;
	end
	end
	
	
	case(instruc[15:12])
	4'b1000:								//Move
	begin
	if(st==a) begin
	adrs=instruc[11:8];
	R=1;
	W=0;
	end
	if(st==b) begin
	adrs=instruc[7:4];
	R=0;
	W=1;
	end
	if(st==c) begin
	st=start;
	count=1;
	W=0;
	end
	end

	4'b1001:						//Load
	begin
	if(st==a) begin
	adrs=instruc[11:8];
	dtin=instruc[7:0];
	R=0;
	W=0;
	L=1;
	S=0;
	end
	if(st==b) begin
	W=1;
	L=0;
	end
	if(st==c) begin
	W=0;
	count=1;
	st=start;
	end
	end

	4'b1010:						//Store
	begin
	if(st==a) begin
	adrs=instruc[11:8];
	R=1;
	W=0;
	L=0;
	S=1;
	end
	if(st==b) begin
	adrs=instruc[7:4];
	R=0;
	W=1;
	S=1;
	end
	if(st==c) begin
	st=start;
	S=0;
	count=1;
	W=0;
	end 
	end

	4'b1011:						//Load from external memory
	begin
	if(st==a) begin
	adrs=instruc[7:4];
	R=0;
	W=0;
	L=1;
	S=1;
	end
	if(st==b) begin
	adrs=instruc[11:8];
	L=0;
	W=1;
	S=0;
	end
	if(st==c) begin
	W=0;
	count=1;
	st=start;
	end
	end

	4'b1111: begin				//Stop
	st=g;
	end

	4'b1101:begin
	if(st==a)begin
	if(flag[0]==1'b1) begin
	countadd=instruc[11:7];
	end
	else begin
	countadd=instruc[6:2];
	end
	end
	if(st==b) begin
	count=1;
	st=start;
	end
	end

	4'b1110:begin
	if(st==a)begin
	if(flag[1]==1'b1) begin
	countadd=instruc[11:7];
	end
	else begin
	countadd=instruc[6:2];
	end
	end
	if(st==b) begin
	count=1;
	st=start;
	end
	end

	4'b1100:						//Store immedieately
	begin
	if(st==a) begin
	dtin=instruc[7:0];
	adrs=4'b0000;
	R=0;
	W=0;
	L=1;
	S=0;
	end
	if(st==b) begin
	L=0;
	W=1;
	end
	if(st==c) begin
	R=1;
	S=1;
	W=0;
	end
	if(st==d) begin
	adrs=instruc[11:8];
	R=0;
	W=1;
	S=1;
	L=0;
	end
	if(st==e) begin
	st=start;
	S=0;
	count=1;
	W=0;
	end 
	end

	

	endcase
	end

endmodule

module eu(adrs,dtin,W,R,cbus,L,out,S,bust,flag);
input wire[3:0] adrs;
input wire[7:0] dtin,bust;
input wire[2:0] cbus;
input W,R, L, S;
output reg[7:0] out ;
output reg[1:0] flag;
wire [7:0] a1, a2,a3,test1,test2,test3,test4,test5,test6,test7;
reg[7:0] mem [0:15];
reg[7:0] bus;
reg [3:0] addbus;
wire [1:0] f;

	always @(*) begin
		if(1) begin
			addbus <= adrs;
		end
		if(L&!S) begin
			bus <= dtin;
		end
		if(W &!S) begin
			mem[addbus] = bus;
		end
		if (R &!S) begin
			bus = mem[addbus];
		end
		if (R & S) begin
			out= mem[addbus];
		end
		if(L&S) begin
			bus<=bust;
		end
		
	end
assign a1 = mem[0];					//Hard coding the registers to perform the operation 
assign a2 = mem[1];

alu ArithmeticLogicUnit(a1, a2, a3, cbus,f);

always @(*) begin
	mem[2] <= a3;
	flag<=f;
end
assign test1=mem[3];	
assign test2=mem[4];
assign test3=mem[5];
assign test4=mem[6];
assign test5=mem[7];
assign test6=mem[8];
assign test7=mem[9];
assign test8=mem[10];
endmodule


module alu(a1,a2,a3,cbus,flag);
input [2:0] cbus;
input [7:0] a1,a2;
output [7:0] a3;
output [1:0] flag;
reg [8:0] res;
wire [7:0] temp;
reg [1:0] f;
assign temp =8'b00000001;
always @(*)begin
case(cbus)
	3'b000 :begin
	 res=a1+a2;
	 f[1]=res[8];
	 if(res==0) begin
		f[0]=1'b1;
		end
	else begin
		f[0]=1'b0;
		end
	end
	3'b001 :begin
	 res=a1-a2;
	 f[1]=res[8];
	 if(res==0) begin
		f[0]=1'b1;
		end
	else begin
		f[0]=1'b0;
		end
	end
	3'b010 :begin
	 res=a1&a2;
	 f[1]=res[8];
	 if(res==0) begin
		f[0]=1'b1;
		end
	else begin
		f[0]=1'b0;
		end
	end
	3'b011 :begin
	 res=a1|a2;
	 f[1]=res[8];
	 if(res==0) begin
		f[0]=1'b1;
		end
	else begin
		f[0]=1'b0;
		end
	end
	3'b100 :begin
	 res=a1<<a2;
	 f[1]=res[8];
	 if(res==0) begin
		f[0]=1'b1;
		end
	else begin
		f[0]=1'b0;
		end
	end
	3'b101 : begin
	 res=a1>>a2;
	 f[1]=res[8];
	 if(res==0) begin
		f[0]=1'b1;
		end
	else begin
		f[0]=1'b0;
		end
	end
	3'b110 :begin
	 res=a1+temp;
	 f[1]=res[8];
	 if(res==0) begin
		f[0]=1'b1;
		end
	else begin
		f[0]=1'b0;
		end
	end
	3'b111 :begin
	 res=a1-temp;
	 f[1]=res[8];
	 if(res==0) begin
		f[0]=1'b1;
		end
	else begin
		f[0]=1'b0;
		end
	end 
	default res=a3 ;
	endcase	
end
assign a3=res[7:0];
assign flag=f;
endmodule

test.v
`timescale 1ns / 1ps

////////////////////////////////////////////////////////////////////////////////
// Company:
// Engineer:
//
// Create Date:   00:50:53 11/06/2017
// Design Name:   mini
// Module Name:   C:/Users/JawaharPC/Documents/Xilinx/mini/test1.v
// Project Name:  mini
// Target Device: 
// Tool versions: 
// Description:
//
// Verilog Test Fixture created by ISE for module: mini
//
// Dependencies:
//
// Revision:
// Revision 0.01 - File Created
// Additional Comments:
//
////////////////////////////////////////////////////////////////////////////////

module test;

    // Inputs
    reg clk;

    // Outputs
    wire L;
    wire W;
    wire R;
    wire S;

    // Instantiate the Unit Under Test (UUT)
    mini uut (
        .clk(clk),
        .L(L),
        .W(W),
        .R(R),
        .S(S)
    );

    initial begin
    $dumpfile("test.vcd");
    $dumpvars(0,test);
 // Initialize Inputs
        clk = 0;
                // Wait 100 ns for global reset to finish
     repeat(10000) begin
     #100 ;
        clk=!clk;
    end
      end 
        // Add stimulus here

   
     
endmodule

test.vcd
$date
	Thu Nov  9 15:16:39 2017
$end
$version
	Icarus Verilog
$end
$timescale
	1ps
$end
$scope module test $end
$var wire 1 ! L $end
$var wire 1 " R $end
$var wire 1 # S $end
$var wire 1 $ W $end
$var reg 1 % clk $end
$scope module uut $end
$var wire 1 ! L $end
$var wire 1 " R $end
$var wire 1 # S $end
$var wire 1 $ W $end
$var wire 4 & adrs [3:0] $end
$var wire 3 ' cbus [2:0] $end
$var wire 1 ( clk $end
$var wire 8 ) dm0 [7:0] $end
$var wire 8 * dm1 [7:0] $end
$var wire 8 + dm2 [7:0] $end
$var wire 8 , dtin [7:0] $end
$var wire 2 - flag [1:0] $end
$var wire 8 . out [7:0] $end
$var reg 8 / bus [7:0] $end
$scope module ControlUnit $end
$var wire 1 ! L $end
$var wire 1 " R $end
$var wire 1 # S $end
$var wire 1 $ W $end
$var wire 4 0 adrs [3:0] $end
$var wire 3 1 cbus [2:0] $end
$var wire 1 ( clk $end
$var wire 1 2 count $end
$var wire 5 3 countadd [4:0] $end
$var wire 8 4 dtin [7:0] $end
$var wire 2 5 flag [1:0] $end
$var wire 16 6 instruc [15:0] $end
$var wire 5 7 pc [4:0] $end
$scope module ProgramCounter $end
$var wire 1 ( clk $end
$var wire 1 2 count $end
$var wire 5 8 countadd [4:0] $end
$var reg 5 9 pc [4:0] $end
$upscope $end
$scope module InstructionDecoder $end
$var wire 1 ( clk $end
$var wire 2 : flag [1:0] $end
$var wire 16 ; instruc [15:0] $end
$var reg 1 < L $end
$var reg 1 = R $end
$var reg 1 > S $end
$var reg 1 ? W $end
$var reg 4 @ a [3:0] $end
$var reg 4 A adrs [3:0] $end
$var reg 4 B b [3:0] $end
$var reg 4 C c [3:0] $end
$var reg 3 D cbus [2:0] $end
$var reg 1 E count $end
$var reg 5 F countadd [4:0] $end
$var reg 4 G d [3:0] $end
$var reg 8 H dtin [7:0] $end
$var reg 4 I e [3:0] $end
$var reg 4 J f [3:0] $end
$var reg 4 K g [3:0] $end
$var reg 4 L st [3:0] $end
$var reg 4 M start [3:0] $end
$upscope $end
$scope module ProgramMemory $end
$var wire 1 ( clk $end
$var wire 5 N pc [4:0] $end
$var reg 16 O instruc [15:0] $end
$upscope $end
$upscope $end
$scope module ExecutionUnit $end
$var wire 1 ! L $end
$var wire 1 " R $end
$var wire 1 # S $end
$var wire 1 $ W $end
$var wire 8 P a1 [7:0] $end
$var wire 8 Q a2 [7:0] $end
$var wire 8 R a3 [7:0] $end
$var wire 4 S adrs [3:0] $end
$var wire 8 T bust [7:0] $end
$var wire 3 U cbus [2:0] $end
$var wire 8 V dtin [7:0] $end
$var wire 2 W f [1:0] $end
$var wire 8 X test1 [7:0] $end
$var wire 8 Y test2 [7:0] $end
$var wire 8 Z test3 [7:0] $end
$var wire 8 [ test4 [7:0] $end
$var wire 8 \ test5 [7:0] $end
$var wire 8 ] test6 [7:0] $end
$var wire 8 ^ test7 [7:0] $end
$var wire 1 _ test8 $end
$var reg 4 ` addbus [3:0] $end
$var reg 8 a bus [7:0] $end
$var reg 2 b flag [1:0] $end
$var reg 8 c out [7:0] $end
$scope module ArithmeticLogicUnit $end
$var wire 8 d a1 [7:0] $end
$var wire 8 e a2 [7:0] $end
$var wire 8 f a3 [7:0] $end
$var wire 3 g cbus [2:0] $end
$var wire 2 h flag [1:0] $end
$var wire 8 i temp [7:0] $end
$var reg 2 j f [1:0] $end
$var reg 9 k res [8:0] $end
$upscope $end
$upscope $end
$upscope $end
$upscope $end
$enddefinitions $end
#0
$dumpvars
b0xxxxxxxx k
bx j
b1 i
bx h
bx g
bx f
bz e
bz d
bx c
bx b
bx a
bx `
z_
bz ^
bz ]
bz \
bz [
bz Z
bz Y
bz X
bx W
bx V
bx U
bx T
bx S
bx R
bz Q
bz P
b1001011000001000 O
b0 N
b0 M
b0 L
b111 K
b110 J
b101 I
bx H
b100 G
b11111 F
0E
bx D
b11 C
b10 B
bx A
b1 @
x?
x>
x=
x<
b1001011000001000 ;
bx :
b0 9
b11111 8
b0 7
b1001011000001000 6
bx 5
bx 4
b11111 3
02
bx 1
bx 0
bx /
bx .
bx -
bx ,
bz +
bz *
bz )
0(
bx '
bx &
0%
x$
x#
x"
x!
$end
#100000
b1000 a
b110 `
0>
0#
1<
1!
0?
0$
0=
0"
b1000 H
b1000 ,
b1000 4
b1000 V
b110 A
b110 &
b110 0
b110 S
b1 L
1%
1(
#200000
0%
0(
#300000
b1000 [
0<
0!
1?
1$
b10 L
1%
1(
#400000
0%
0(
#500000
b1001011100000010 O
b1001011100000010 6
b1001011100000010 ;
b1 9
b1 7
b1 N
1E
12
0?
0$
b0 L
1%
1(
#600000
0%
0(
#700000
b10 a
b111 `
1<
1!
b10 H
b10 ,
b10 4
b10 V
b111 A
b111 &
b111 0
b111 S
0E
02
b1 L
1%
1(
#800000
0%
0(
#900000
b10 \
0<
0!
1?
1$
b10 L
1%
1(
#1000000
0%
0(
#1100000
b1001100000000000 O
b1001100000000000 6
b1001100000000000 ;
b10 9
b10 7
b10 N
1E
12
0?
0$
b0 L
1%
1(
#1200000
0%
0(
#1300000
b0 a
b1000 `
1<
1!
b0 H
b0 ,
b0 4
b0 V
b1000 A
b1000 &
b1000 0
b1000 S
0E
02
b1 L
1%
1(
#1400000
0%
0(
#1500000
b0 ]
0<
0!
1?
1$
b10 L
1%
1(
#1600000
0%
0(
#1700000
b100001100100xxxx O
b100001100100xxxx 6
b100001100100xxxx ;
b11 9
b11 7
b11 N
1E
12
0?
0$
b0 L
1%
1(
#1800000
0%
0(
#1900000
b1000 a
b110 `
1=
1"
b110 A
b110 &
b110 0
b110 S
0E
02
b1 L
1%
1(
#2000000
0%
0(
#2100000
b1000 Y
b100 `
1?
1$
0=
0"
b100 A
b100 &
b100 0
b100 S
b10 L
1%
1(
#2200000
0%
0(
#2300000
b1010001110100 O
b1010001110100 6
b1010001110100 ;
b100 9
b100 7
b100 N
0?
0$
1E
12
b0 L
1%
1(
#2400000
0%
0(
#2500000
1=
1"
0E
02
b1 L
1%
1(
#2600000
0%
0(
#2700000
b1000 P
b1000 d
b0 `
b0 A
b0 &
b0 0
b0 S
0=
0"
1?
1$
b10 L
1%
1(
#2800000
0%
0(
#2900000
b10 a
b111 `
b111 A
b111 &
b111 0
b111 S
1=
1"
0?
0$
b11 L
1%
1(
#3000000
0%
0(
#3100000
b10 Q
b10 e
b1 `
b1 A
b1 &
b1 0
b1 S
0=
0"
1?
1$
b100 L
1%
1(
#3200000
0%
0(
#3300000
b0 b
b0 -
b0 5
b0 :
b110 R
b110 f
b0 j
b0 W
b0 h
b110 k
b1 D
b1 '
b1 1
b1 U
b1 g
0?
0$
b101 L
1%
1(
#3400000
0%
0(
#3500000
b110 a
b10 `
b10 A
b10 &
b10 0
b10 S
1=
1"
b110 L
1%
1(
#3600000
0%
0(
#3700000
b110 Y
b100 `
b100001100011xxxx O
b100001100011xxxx 6
b100001100011xxxx ;
b101 9
b101 7
b101 N
1E
12
b100 A
b100 &
b100 0
b100 S
1?
1$
0=
0"
b0 L
1%
1(
#3800000
0%
0(
#3900000
b1000 a
b110 `
0?
0$
1=
1"
b110 A
b110 &
b110 0
b110 S
0E
02
b1 L
1%
1(
#4000000
0%
0(
#4100000
b1000 X
b11 `
1?
1$
0=
0"
b11 A
b11 &
b11 0
b11 S
b10 L
1%
1(
#4200000
0%
0(
#4300000
b100010001001xxxx O
b100010001001xxxx 6
b100010001001xxxx ;
b110 9
b110 7
b110 N
0?
0$
1E
12
b0 L
1%
1(
#4400000
0%
0(
#4500000
b0 a
b1000 `
1=
1"
b1000 A
b1000 &
b1000 0
b1000 S
0E
02
b1 L
1%
1(
#4600000
0%
0(
#4700000
b0 ^
b1001 `
1?
1$
0=
0"
b1001 A
b1001 &
b1001 0
b1001 S
b10 L
1%
1(
#4800000
0%
0(
#4900000
b100001000101xxxx O
b100001000101xxxx 6
b100001000101xxxx ;
b111 9
b111 7
b111 N
0?
0$
1E
12
b0 L
1%
1(
#5000000
0%
0(
#5100000
b110 a
b100 `
1=
1"
b100 A
b100 &
b100 0
b100 S
0E
02
b1 L
1%
1(
#5200000
0%
0(
#5300000
b110 Z
b101 `
1?
1$
0=
0"
b101 A
b101 &
b101 0
b101 S
b10 L
1%
1(
#5400000
0%
0(
#5500000
b100010011000 O
b100010011000 6
b100010011000 ;
b1000 9
b1000 7
b1000 N
0?
0$
1E
12
b0 L
1%
1(
#5600000
0%
0(
#5700000
b0 a
b1000 `
b1000 A
b1000 &
b1000 0
b1000 S
1=
1"
0E
02
b1 L
1%
1(
#5800000
0%
0(
#5900000
b10 b
b10 -
b10 5
b10 :
b11111110 R
b11111110 f
b10 j
b10 W
b10 h
b111111110 k
b0 P
b0 d
b0 `
b0 A
b0 &
b0 0
b0 S
0=
0"
1?
1$
b10 L
1%
1(
#6000000
0%
0(
#6100000
b1001 `
b1001 A
b1001 &
b1001 0
b1001 S
1=
1"
0?
0$
b11 L
1%
1(
#6200000
0%
0(
#6300000
b1 b
b1 -
b1 5
b1 :
b0 R
b0 f
b1 j
b1 W
b1 h
b0 k
b0 Q
b0 e
b1 `
b1 A
b1 &
b1 0
b1 S
0=
0"
1?
1$
b100 L
1%
1(
#6400000
0%
0(
#6500000
b1 j
b0 D
b0 '
b0 1
b0 U
b0 g
0?
0$
b101 L
1%
1(
#6600000
0%
0(
#6700000
b10 `
b10 A
b10 &
b10 0
b10 S
1=
1"
b110 L
1%
1(
#6800000
0%
0(
#6900000
b1000 `
b11000110110 O
b11000110110 6
b11000110110 ;
b1001 9
b1001 7
b1001 N
1E
12
b1000 A
b1000 &
b1000 0
b1000 S
1?
1$
0=
0"
b0 L
1%
1(
#7000000
0%
0(
#7100000
b1000 a
b110 `
b110 A
b110 &
b110 0
b110 S
1=
1"
0?
0$
0E
02
b1 L
1%
1(
#7200000
0%
0(
#7300000
b0 b
b0 -
b0 5
b0 :
b1000 R
b1000 f
b0 W
b0 h
b0 j
b1000 k
b1000 P
b1000 d
b0 `
b0 A
b0 &
b0 0
b0 S
0=
0"
1?
1$
b10 L
1%
1(
#7400000
0%
0(
#7500000
b11 `
b11 A
b11 &
b11 0
b11 S
1=
1"
0?
0$
b11 L
1%
1(
#7600000
0%
0(
#7700000
b10000 R
b10000 f
b0 j
b10000 k
b1000 Q
b1000 e
b1 `
b1 A
b1 &
b1 0
b1 S
0=
0"
1?
1$
b100 L
1%
1(
#7800000
0%
0(
#7900000
0?
0$
b101 L
1%
1(
#8000000
0%
0(
#8100000
b10000 a
b10 `
b10 A
b10 &
b10 0
b10 S
1=
1"
b110 L
1%
1(
#8200000
0%
0(
#8300000
b10000 [
b110 `
b11100101101100xx O
b11100101101100xx 6
b11100101101100xx ;
b1010 9
b1010 7
b1010 N
1E
12
b110 A
b110 &
b110 0
b110 S
1?
1$
0=
0"
b0 L
1%
1(
#8400000
0%
0(
#8500000
b1100 F
b1100 3
b1100 8
0E
02
b1 L
1%
1(
#8600000
0%
0(
#8700000
b1110101xxxxxxxx O
b1110101xxxxxxxx 6
b1110101xxxxxxxx ;
b1100 9
b1100 7
b1100 N
1E
12
b0 L
1%
1(
#8800000
0%
0(
#8900000
b110 a
b101 `
b101 A
b101 &
b101 0
b101 S
1=
1"
0?
0$
b11111 F
b11111 3
b11111 8
0E
02
b1 L
1%
1(
#9000000
0%
0(
#9100000
b1110 R
b1110 f
b0 j
b1110 k
b110 P
b110 d
b0 `
b0 A
b0 &
b0 0
b0 S
0=
0"
1?
1$
b10 L
1%
1(
#9200000
0%
0(
#9300000
bx a
bx `
bx A
bx &
bx 0
bx S
1=
1"
0?
0$
b11 L
1%
1(
#9400000
0%
0(
#9500000
bx0 b
bx0 -
bx0 5
bx0 :
bx R
bx f
bx0 j
bx0 W
bx0 h
bx k
bx Q
bx e
b1 `
b1 A
b1 &
b1 0
b1 S
0=
0"
1?
1$
b100 L
1%
1(
#9600000
0%
0(
#9700000
b0 b
b0 -
b0 5
b0 :
b101 R
b101 f
b0 j
b0 W
b0 h
b101 k
b111 D
b111 '
b111 1
b111 U
b111 g
0?
0$
b101 L
1%
1(
#9800000
0%
0(
#9900000
b101 a
b10 `
b10 A
b10 &
b10 0
b10 S
1=
1"
b110 L
1%
1(
#10000000
0%
0(
#10100000
b101 Z
b101 `
b11010111001000xx O
b11010111001000xx 6
b11010111001000xx ;
b1101 9
b1101 7
b1101 N
1E
12
b101 A
b101 &
b101 0
b101 S
1?
1$
0=
0"
b0 L
1%
1(
#10200000
0%
0(
#10300000
b1000 F
b1000 3
b1000 8
0E
02
b1 L
1%
1(
#10400000
0%
0(
#10500000
b100010011000 O
b100010011000 6
b100010011000 ;
b1000 9
b1000 7
b1000 N
1E
12
b0 L
1%
1(
#10600000
0%
0(
#10700000
b0 a
b1000 `
b1000 A
b1000 &
b1000 0
b1000 S
1=
1"
0?
0$
b11111 F
b11111 3
b11111 8
0E
02
b1 L
1%
1(
#10800000
0%
0(
#10900000
b10 b
b10 -
b10 5
b10 :
b11111111 R
b11111111 f
b10 j
b10 W
b10 h
b111111111 k
b0 P
b0 d
b0 `
b0 A
b0 &
b0 0
b0 S
0=
0"
1?
1$
b10 L
1%
1(
#11000000
0%
0(
#11100000
b1001 `
b1001 A
b1001 &
b1001 0
b1001 S
1=
1"
0?
0$
b11 L
1%
1(
#11200000
0%
0(
#11300000
b10 j
b0 Q
b0 e
b1 `
b1 A
b1 &
b1 0
b1 S
0=
0"
1?
1$
b100 L
1%
1(
#11400000
0%
0(
#11500000
b1 b
b1 -
b1 5
b1 :
b0 R
b0 f
b1 j
b1 W
b1 h
b0 k
b0 D
b0 '
b0 1
b0 U
b0 g
0?
0$
b101 L
1%
1(
#11600000
0%
0(
#11700000
b10 `
b10 A
b10 &
b10 0
b10 S
1=
1"
b110 L
1%
1(
#11800000
0%
0(
#11900000
b1000 `
b11000110110 O
b11000110110 6
b11000110110 ;
b1001 9
b1001 7
b1001 N
1E
12
b1000 A
b1000 &
b1000 0
b1000 S
1?
1$
0=
0"
b0 L
1%
1(
#12000000
0%
0(
#12100000
b10000 a
b110 `
b110 A
b110 &
b110 0
b110 S
1=
1"
0?
0$
0E
02
b1 L
1%
1(
#12200000
0%
0(
#12300000
b0 b
b0 -
b0 5
b0 :
b10000 R
b10000 f
b0 W
b0 h
b0 j
b10000 k
b10000 P
b10000 d
b0 `
b0 A
b0 &
b0 0
b0 S
0=
0"
1?
1$
b10 L
1%
1(
#12400000
0%
0(
#12500000
b1000 a
b11 `
b11 A
b11 &
b11 0
b11 S
1=
1"
0?
0$
b11 L
1%
1(
#12600000
0%
0(
#12700000
b11000 R
b11000 f
b0 j
b11000 k
b1000 Q
b1000 e
b1 `
b1 A
b1 &
b1 0
b1 S
0=
0"
1?
1$
b100 L
1%
1(
#12800000
0%
0(
#12900000
0?
0$
b101 L
1%
1(
#13000000
0%
0(
#13100000
b11000 a
b10 `
b10 A
b10 &
b10 0
b10 S
1=
1"
b110 L
1%
1(
#13200000
0%
0(
#13300000
b11000 [
b110 `
b11100101101100xx O
b11100101101100xx 6
b11100101101100xx ;
b1010 9
b1010 7
b1010 N
1E
12
b110 A
b110 &
b110 0
b110 S
1?
1$
0=
0"
b0 L
1%
1(
#13400000
0%
0(
#13500000
b1100 F
b1100 3
b1100 8
0E
02
b1 L
1%
1(
#13600000
0%
0(
#13700000
b1110101xxxxxxxx O
b1110101xxxxxxxx 6
b1110101xxxxxxxx ;
b1100 9
b1100 7
b1100 N
1E
12
b0 L
1%
1(
#13800000
0%
0(
#13900000
b101 a
b101 `
b101 A
b101 &
b101 0
b101 S
1=
1"
0?
0$
b11111 F
b11111 3
b11111 8
0E
02
b1 L
1%
1(
#14000000
0%
0(
#14100000
b1101 R
b1101 f
b0 j
b1101 k
b101 P
b101 d
b0 `
b0 A
b0 &
b0 0
b0 S
0=
0"
1?
1$
b10 L
1%
1(
#14200000
0%
0(
#14300000
bx a
bx `
bx A
bx &
bx 0
bx S
1=
1"
0?
0$
b11 L
1%
1(
#14400000
0%
0(
#14500000
bx0 b
bx0 -
bx0 5
bx0 :
bx R
bx f
bx0 j
bx0 W
bx0 h
bx k
bx Q
bx e
b1 `
b1 A
b1 &
b1 0
b1 S
0=
0"
1?
1$
b100 L
1%
1(
#14600000
0%
0(
#14700000
b0 b
b0 -
b0 5
b0 :
b100 R
b100 f
b0 j
b0 W
b0 h
b100 k
b111 D
b111 '
b111 1
b111 U
b111 g
0?
0$
b101 L
1%
1(
#14800000
0%
0(
#14900000
b100 a
b10 `
b10 A
b10 &
b10 0
b10 S
1=
1"
b110 L
1%
1(
#15000000
0%
0(
